setup.py
src/django_test_extensions.egg-info/PKG-INFO
src/django_test_extensions.egg-info/SOURCES.txt
src/django_test_extensions.egg-info/dependency_links.txt
src/django_test_extensions.egg-info/requires.txt
src/django_test_extensions.egg-info/top_level.txt
src/test_extensions/__init__.py
src/test_extensions/common.py
src/test_extensions/django_common.py
src/test_extensions/twill.py
src/test_extensions/management/__init__.py
src/test_extensions/management/commands/__init__.py
src/test_extensions/management/commands/runtester.py
src/test_extensions/management/commands/test.py
src/test_extensions/testrunners/__init__.py
src/test_extensions/testrunners/codecoverage.py
src/test_extensions/testrunners/figleafcoverage.py
src/test_extensions/testrunners/nodatabase.py
src/test_extensions/testrunners/xmloutput.py
src/test_extensions/testrunners/xmlunit/__init__.py
src/test_extensions/testrunners/xmlunit/unittest.py