Metadata-Version: 1.0
Name: django-test-extensions
Version: 0.14
Summary: A few classes to make testing django applications easier
Home-page: http://github.com/garethr/django-test-extensions/
Author: Gareth Rushgrove
Author-email: gareth@morethanseven.net
License: MIT License
Keywords: django testing
Platform: UNKNOWN
Classifier: Intended Audience :: Developers
Classifier: License :: OSI Approved :: MIT License
Classifier: Operating System :: OS Independent
Classifier: Programming Language :: Python
Classifier: Topic :: Software Development :: Testing
